deepgen/__init__.py
deepgen/utils.py
deepgen/gan/__init__.py
deepgen/gan/base.py
deepgen/gan/bgan.py
deepgen/gan/cgan.py
deepgen/gan/dcgan.py
deepgen/gan/gan.py
deepgen-0.0.11.dist-info/LICENSE
deepgen-0.0.11.dist-info/METADATA
deepgen-0.0.11.dist-info/WHEEL
deepgen-0.0.11.dist-info/top_level.txt
deepgen-0.0.11.dist-info/RECORD
