Metadata-Version: 2.1
Name: deepgen
Version: 0.0.11
Summary: A Collection of modern Deep Generative Models
Home-page: https://github.com/vndee/deepgen
Author: Duy Huynh
Author-email: hvd.huynhduy@gmail.com
License: MIT
Platform: UNKNOWN
Classifier: License :: OSI Approved :: MIT License
Classifier: Programming Language :: Python :: 3
Classifier: Programming Language :: Python :: 3.7
Requires-Dist: torch (==1.1.0)
Requires-Dist: torchvision (==0.3.0)
Requires-Dist: tqdm (==4.32.2)
